exce/__init__.py
exce/cantrips/__init__.py
exce-0.1.0.dist-info/licenses/LICENSE
exce-0.1.0.dist-info/WHEEL
exce-0.1.0.dist-info/METADATA
exce-0.1.0.dist-info/RECORD
