Metadata-Version: 2.4
Name: exce
Version: 0.1.0
Summary: IPython magic to export code from .qmd cells to python .py files
Author-email: Fenke Meijer <fenkemeijer@gmail.com>
License-Expression: GPL-3.0-or-later
License-File: LICENSE
Project-URL: Home, https://codeberg.org/fenke/exce
